atomsgraph/__init__.py
atomsgraph/version.py
atomsgraph-0.1.0.dist-info/LICENSE
atomsgraph-0.1.0.dist-info/METADATA
atomsgraph-0.1.0.dist-info/WHEEL
atomsgraph-0.1.0.dist-info/top_level.txt
atomsgraph-0.1.0.dist-info/RECORD
