Metadata-Version: 2.1
Name: atomsgraph
Version: 0.1.0
Summary: Python library for interacting with an atoms graph
Home-page: https://github.com/muhrin/atomsgraph.git
Author: Martin Uhrin
Author-email: martin.uhrin.10@ucl.ac.uk
License: LGPLv3
Keywords: machine learning,atomic descriptor,moment invariants
Platform: UNKNOWN
Classifier: License :: OSI Approved :: GNU Lesser General Public License v3 or later (LGPLv3+)
Classifier: Programming Language :: Python :: 3.6
Classifier: Programming Language :: Python :: 3.7
Classifier: Programming Language :: Python :: 3.8
Classifier: Programming Language :: Python :: 3.9
Requires-Python: >=3.6
Requires-Dist: gremlinpython
Provides-Extra: dev
Requires-Dist: ipython ; extra == 'dev'
Requires-Dist: pip ; extra == 'dev'
Requires-Dist: pytest (~=5.4) ; extra == 'dev'
Requires-Dist: pytest-cov ; extra == 'dev'
Requires-Dist: pre-commit (~=2.2) ; extra == 'dev'
Requires-Dist: prospector ; extra == 'dev'
Requires-Dist: pylint (==2.5.2) ; extra == 'dev'
Requires-Dist: twine ; extra == 'dev'
Requires-Dist: yapf ; extra == 'dev'
